pyfdupes/__init__.py
pyfdupes/cli.py
pyfdupes/fdupes.py
pyfdupes/utils.py
pyfdupes-0.1.0.dist-info/entry_points.txt
pyfdupes-0.1.0.dist-info/METADATA
pyfdupes-0.1.0.dist-info/WHEEL
pyfdupes-0.1.0.dist-info/LICENSE
pyfdupes-0.1.0.dist-info/RECORD
