Metadata-Version: 2.1
Name: pyfdupes
Version: 0.1.0
Summary: Find and delete duplicate files using fdupes
Home-page: https://github.com/essembeh/pyfdupes
License: Apache-2.0
Author: Sébastien MB
Author-email: seb@essembeh.org
Requires-Python: >=3.9,<4.0
Classifier: Development Status :: 4 - Beta
Classifier: License :: OSI Approved :: Apache Software License
Classifier: Programming Language :: Python :: 3
Classifier: Programming Language :: Python :: 3.9
Classifier: Programming Language :: Python :: 3.10
Classifier: Programming Language :: Python :: 3.11
Classifier: Topic :: Utilities
Requires-Dist: colorama (>=0.4.5,<0.5.0)
